odoo10_addon_base_external_system-10.0.1.0.0-py2.7-nspkg.pth
odoo/addons/base_external_system/README.rst
odoo/addons/base_external_system/__init__.py
odoo/addons/base_external_system/__manifest__.py
odoo/addons/base_external_system/demo/external_system_os_demo.xml
odoo/addons/base_external_system/models/__init__.py
odoo/addons/base_external_system/models/external_system.py
odoo/addons/base_external_system/models/external_system_adapter.py
odoo/addons/base_external_system/models/external_system_os.py
odoo/addons/base_external_system/security/ir.model.access.csv
odoo/addons/base_external_system/static/description/icon.png
odoo/addons/base_external_system/tests/__init__.py
odoo/addons/base_external_system/tests/common.py
odoo/addons/base_external_system/tests/test_external_system.py
odoo/addons/base_external_system/tests/test_external_system_adapter.py
odoo/addons/base_external_system/tests/test_external_system_os.py
odoo/addons/base_external_system/views/external_system_view.xml
odoo10_addon_base_external_system-10.0.1.0.0.dist-info/DESCRIPTION.rst
odoo10_addon_base_external_system-10.0.1.0.0.dist-info/METADATA
odoo10_addon_base_external_system-10.0.1.0.0.dist-info/RECORD
odoo10_addon_base_external_system-10.0.1.0.0.dist-info/WHEEL
odoo10_addon_base_external_system-10.0.1.0.0.dist-info/metadata.json
odoo10_addon_base_external_system-10.0.1.0.0.dist-info/namespace_packages.txt
odoo10_addon_base_external_system-10.0.1.0.0.dist-info/top_level.txt
